AUTHORS
ChangeLog
LICENSE
MANIFEST.in
README.rst
requirements.txt
setup.cfg
setup.py
bsncpsec/__init__.py
bsncpsec/bsncpsec.py
bsncpsec/hooks.py
bsncpsec.egg-info/PKG-INFO
bsncpsec.egg-info/SOURCES.txt
bsncpsec.egg-info/dependency_links.txt
bsncpsec.egg-info/entry_points.txt
bsncpsec.egg-info/not-zip-safe
bsncpsec.egg-info/pbr.json
bsncpsec.egg-info/requires.txt
bsncpsec.egg-info/top_level.txt
etc/bsncpsec_config/config.yaml