Metadata-Version: 1.1
Name: bsncpsec
Version: 0.0.1
Summary: Tool to secure BCF control plane
Home-page: http://www.bigswitch.com/
Author: Big Switch Networks
Author-email: support@bigswitch.com
License: UNKNOWN
Platform: UNKNOWN
Classifier: Environment :: OpenStack
Classifier: Intended Audience :: Information Technology
Classifier: Intended Audience :: System Administrators
Classifier: License :: OSI Approved :: Apache Software License
Classifier: Operating System :: POSIX :: Linux
Classifier: Programming Language :: Python
Classifier: Programming Language :: Python :: 2
Classifier: Programming Language :: Python :: 2.7
